{
    "total_processed": 3,
    "found": 3,
    "not_found": 0,
    "results": [
        {
            "title": "",
            "page_url": "https://www.fancode.com/cricket/tour/pakistan-tour-of-bangladesh-2026-19498402/video-highlights/bangladesh-beat-pakistan-by-11-runs-3rd-odi-214239",
            "video_ids": [
                "19482712",
                "19449261",
                "213571",
                "18834978",
                "19512144",
                "7378",
                "141148",
                "6001",
                "19464638",
                "213825",
                "214248",
                "141033",
                "17031406",
                "18961588",
                "19495826",
                "141310",
                "5572",
                "213820",
                "214225",
                "140716",
                "5986",
                "5995",
                "19271281",
                "19477533",
                "141364",
                "140465",
                "6007",
                "19298131",
                "141147",
                "5806",
                "19322536",
                "19245183",
                "214227",
                "214236",
                "18899297",
                "19428328",
                "19477532",
                "214127",
                "19324161",
                "214126",
                "214246",
                "131104",
                "6002",
                "5488",
                "214224",
                "141304",
                "141222",
                "49158",
                "140954",
                "19298465",
                "5971",
                "19298130",
                "19377161",
                "214237",
                "19291235",
                "42406",
                "214241",
                "49148",
                "141149",
                "18835060",
                "19253270",
                "49146",
                "18801700",
                "19498402",
                "19322535",
                "19298054",
                "213830",
                "8",
                "18884118",
                "19322538",
                "19417899",
                "141365",
                "19446296",
                "19484334",
                "5655",
                "131102",
                "5427",
                "131107",
                "19291236",
                "213821",
                "6010",
                "214144",
                "213786",
                "141150",
                "49157",
                "5489",
                "214247",
                "18899300",
                "141202",
                "141203",
                "141219",
                "181733",
                "141204",
                "19457045",
                "214239",
                "49151",
                "5992",
                "19293085",
                "5956",
                "32622934",
                "19497761"
            ],
            "m3u8_links": [
                "https://in-mc-vod.fancode.com/vision/skillup-uploads/cms-media-rth/1773596601/d8e7280e-4643-4710-b4e9-ff3f615621a3_1773596577497/index.m3u8",
                "https://in-mc-vod.fancode.com/delhi/131106_english_hls_8d264546df32084_1ta-di_h264_backup/vod_640_index.m3u8"
            ],
            "status": "found"
        },
        {
            "title": "COMPLETEDBangladeshPakistanPakistan tour of Bangladesh, 20263rd ODIBangladesh beat Pakistan by 11 runsHIGHLIGHTS",
            "page_url": "https://www.fancode.com/cricket/tour/pakistan-tour-of-bangladesh-2026-19498402/video-highlights/bangladesh-beat-pakistan-by-11-runs-3rd-odi-214239",
            "video_ids": [
                "19482712",
                "19449261",
                "213571",
                "18834978",
                "19512144",
                "7378",
                "141148",
                "6001",
                "19464638",
                "213825",
                "214248",
                "141033",
                "17031406",
                "18961588",
                "19495826",
                "141310",
                "5572",
                "213820",
                "214225",
                "140716",
                "5986",
                "5995",
                "19271281",
                "19477533",
                "141364",
                "140465",
                "6007",
                "19298131",
                "141147",
                "5806",
                "19322536",
                "19245183",
                "214227",
                "214236",
                "18899297",
                "19428328",
                "19477532",
                "214127",
                "19324161",
                "214126",
                "214246",
                "131104",
                "6002",
                "5488",
                "214224",
                "141304",
                "141222",
                "49158",
                "140954",
                "19298465",
                "5971",
                "19298130",
                "19377161",
                "214237",
                "19291235",
                "42406",
                "214241",
                "49148",
                "141149",
                "18835060",
                "19253270",
                "49146",
                "18801700",
                "19498402",
                "19322535",
                "19298054",
                "213830",
                "8",
                "18884118",
                "19322538",
                "19417899",
                "141365",
                "19446296",
                "19484334",
                "5655",
                "131102",
                "5427",
                "131107",
                "19291236",
                "213821",
                "6010",
                "214144",
                "213786",
                "141150",
                "49157",
                "5489",
                "214247",
                "18899300",
                "141202",
                "141203",
                "141219",
                "181733",
                "141204",
                "19457045",
                "214239",
                "49151",
                "5992",
                "19293085",
                "5956",
                "32622934",
                "19497761"
            ],
            "m3u8_links": [
                "https://in-mc-vod.fancode.com/vision/skillup-uploads/cms-media-rth/1773596601/d8e7280e-4643-4710-b4e9-ff3f615621a3_1773596577497/index.m3u8",
                "https://in-mc-vod.fancode.com/delhi/131106_english_hls_8d264546df32084_1ta-di_h264_backup/vod_640_index.m3u8"
            ],
            "status": "found"
        },
        {
            "title": "SPECIAL28:52ABD reviews India's historic T20 WC campaign",
            "page_url": "https://www.fancode.com/cricket/tour/tour-0/video-highlights/abd-reviews-indias-historic-t20-wc-campaign-213673",
            "video_ids": [
                "19291236",
                "19298130",
                "19298131",
                "19322536",
                "19377161",
                "214237",
                "19449261",
                "213673",
                "19291235",
                "42406",
                "18834978",
                "214241",
                "19512144",
                "19245183",
                "214227",
                "19253270",
                "7378",
                "214236",
                "18899297",
                "18801700",
                "19428328",
                "214247",
                "18899300",
                "19322535",
                "19298054",
                "8",
                "19477532",
                "19324161",
                "214248",
                "17031406",
                "19322538",
                "18961588",
                "214246",
                "19446296",
                "214225",
                "214239",
                "214224",
                "19271281",
                "19293085",
                "19477533",
                "19298465",
                "32622934",
                "19497761"
            ],
            "m3u8_links": [
                "https://in-mc-vod.fancode.com/vision/skillup-uploads/cms-media/1773315852/360-SHow---S08E09---Draft-2/index.m3u8",
                "https://in-mc-vod.fancode.com/delhi/131106_english_hls_8d264546df32084_1ta-di_h264_backup/vod_640_index.m3u8"
            ],
            "status": "found"
        }
    ]
}